{
  "html": "<div class=\"election-headline__wrapper\"><style>.fc-container--story-package .fc-item.facia-snap-embed{background-color:transparent!important}h1.election--headline{font-size:34px;line-height:34px;color:#333;font-weight:100;letter-spacing:-1px}@media all and (min-width:61.25em){h1.election--headline{font-size:80px;line-height:84px}}</style><h1 class=\"election--headline\">A headline about the election results which</h1>\n</div>",
  "previous": "",
  "refreshStatus": true,
  "url": "https://www.theguardian.com/us-news/live/2016/nov/04/donald-trump-hillary-clinton-swing-states-election-2016-campaign-live",
  "headline": "Us Election Headline",
  "trailText": "all the latest from the election"
}